xplane_apt_convert/__init__.py
xplane_apt_convert/__main__.py
xplane_apt_convert/base.py
xplane_apt_convert/classes.py
xplane_apt_convert/cli.py
xplane_apt_convert/geometry.py
xplane_apt_convert/iterators.py
xplane_apt_convert-0.5.6.dist-info/LICENSE
xplane_apt_convert-0.5.6.dist-info/METADATA
xplane_apt_convert-0.5.6.dist-info/WHEEL
xplane_apt_convert-0.5.6.dist-info/top_level.txt
xplane_apt_convert-0.5.6.dist-info/RECORD
