Metadata-Version: 2.1
Name: xplane_apt_convert
Version: 0.5.6
Summary: Convert X-Plane airport data to GIS-friendly formats like GeoJSON or ESRI Shapefile.
Author-email: Carlos Bergillos <c.bergillos.v@gmail.com>
License: MIT
Project-URL: Source Code, https://github.com/CarlosBergillos/xplane_apt_convert
Keywords: geojson,gis,geopackage,airport,shapefile,ogr,airports,fiona,xplane,geobuf,gpkg,flatgeobuf
Classifier: License :: OSI Approved :: MIT License
Classifier: Operating System :: OS Independent
Classifier: Programming Language :: Python
Classifier: Programming Language :: Python :: 3
Classifier: Programming Language :: Python :: 3.6
Classifier: Programming Language :: Python :: 3.7
Classifier: Programming Language :: Python :: 3.8
Classifier: Programming Language :: Python :: 3.9
Classifier: Programming Language :: Python :: 3.10
Classifier: Programming Language :: Python :: 3.11
Classifier: Programming Language :: Python :: 3.12
Classifier: Topic :: Software Development :: Libraries :: Python Modules
Classifier: Topic :: Scientific/Engineering :: GIS
Classifier: Topic :: Games/Entertainment :: Simulation
Classifier: Development Status :: 4 - Beta
Classifier: Intended Audience :: Science/Research
Classifier: Intended Audience :: End Users/Desktop
Requires-Python: >=3.6
License-File: LICENSE
Requires-Dist: bezier
Requires-Dist: fiona
Requires-Dist: numpy
Requires-Dist: rich
Requires-Dist: typer
Requires-Dist: xplane-airports
